exmp1/__init__.py
exmp1/armazenamento.py
exmp1/consulta.py
exmp1/interacao.py
exemp1-0.0.1.dist-info/LICENSE.txt
exemp1-0.0.1.dist-info/METADATA
exemp1-0.0.1.dist-info/WHEEL
exemp1-0.0.1.dist-info/top_level.txt
exemp1-0.0.1.dist-info/RECORD
