Metadata-Version: 2.1
Name: exemp1
Version: 0.0.1
Summary: Pacote python guardar e consultar dados
Home-page: https://github.com
Author: Vinicius Augusto de Moraes Rayol
Author-email: vinicius22070202@aluno.cesupa.br
License: MIT License
Keywords: Pacote
License-File: LICENSE.txt
